savitrigen/__init__.py
savitrigen/__main__.py
savitrigen/bootstrap.py
savitrigen/cache.py
savitrigen/commandline.py
savitrigen/logging.py
savitrigen/path.py
savitrigen/source.py
savitrigen/userdir.py
savitrigen/util.py
savitrigen/data/config.yml
savitrigen/data/presets/iptv.yml
savitrigen/data/presets/sample.yml
savitrigen/guideline/__init__.py
savitrigen/guideline/guideline.py
savitrigen/guideline/rules.py
savitrigen/schema/__init__.py
savitrigen/schema/backend.py
savitrigen/schema/codegen.py
savitrigen/schema/frontend.py
savitrigen/schema/project.py
savitrigen/template/__init__.py
savitrigen/template/backend/__init__.py
savitrigen/template/backend/controller.py
savitrigen/template/backend/imports.py
savitrigen/template/backend/index.py
savitrigen/template/backend/model.py
savitrigen/template/frontend/__init__.py
savitrigen/template/frontend/component.py
savitrigen/template/frontend/extension.py
savitrigen/template/frontend/imports.py
savitrigen/template/frontend/index.py
savitrigen/tree/__init__.py
savitrigen/tree/abstract.py
savitrigen/tree/backend.py
savitrigen/tree/frontend.py
savitrigen/tree/project.py
savitrigen-0.0.96.data/scripts/savitrigen
savitrigen-0.0.96.dist-info/LICENSE
savitrigen-0.0.96.dist-info/METADATA
savitrigen-0.0.96.dist-info/WHEEL
savitrigen-0.0.96.dist-info/top_level.txt
savitrigen-0.0.96.dist-info/RECORD
