Metadata-Version: 2.1
Name: savitrigen
Version: 0.0.96
Summary: Savitri code generator
Author: João Santos
Author-email: joaosan177@gmail.com
License: ISC
License-File: LICENSE
Requires-Dist: multipledispatch (==0.6.0)
Requires-Dist: pyyaml (==6.0)
